PyRexBot/__init__.py
PyRexBot/pyrexbot.py
PyRexBot-1.0.4.dist-info/LICENSE
PyRexBot-1.0.4.dist-info/METADATA
PyRexBot-1.0.4.dist-info/WHEEL
PyRexBot-1.0.4.dist-info/top_level.txt
PyRexBot-1.0.4.dist-info/RECORD
