Metadata-Version: 2.1
Name: PyRexBot
Version: 1.0.4
Summary: PyBotRex simplifies Telegram bot creation with a clean and intuitive interface for commands, messaging, buttons, and more.
Home-page: https://github.com/TraxDinosaur/PyRexBot
Author: TraxDinosaur
Keywords: Telegram Bot,Python Telegram Bot,Telegram API,Bot Development,Python Bot Library,Interactive Bots,PyBotRex,Bot Framework,Telegram Python Bot,Telegram Bot Toolkit
Classifier: Programming Language :: Python :: 3
Classifier: License :: OSI Approved
Classifier: Operating System :: OS Independent
Requires-Python: >=3.7
License-File: LICENSE
Requires-Dist: python-telegram-bot>=20.0
